jsonfilelogger/__init__.py
jsonfilelogger/custom_encoder.py
jsonfilelogger/logger.py
tests/__init__.py
tests/test_logger.py
jsonfilelogger-1.1.0.dist-info/LICENSE
jsonfilelogger-1.1.0.dist-info/METADATA
jsonfilelogger-1.1.0.dist-info/WHEEL
jsonfilelogger-1.1.0.dist-info/top_level.txt
jsonfilelogger-1.1.0.dist-info/RECORD
