Metadata-Version: 2.1
Name: jsonfilelogger
Version: 1.1.0
Summary: A simple json file logger for Python
Home-page: https://github.com/ManuDeBuck/python-json-filelogger
Author: Manu De Buck
Author-email: manu@mdebuck.org
License: UNKNOWN
Platform: UNKNOWN
Classifier: Programming Language :: Python :: 3
Classifier: License :: OSI Approved :: MIT License
Classifier: Operating System :: OS Independent
Requires-Python: >=3.6
License-File: LICENSE
